{
  "app-id": "com.dosbox.DOSBox",
  "runtime": "org.freedesktop.Platform",
  "runtime-version": "19.08",
  "sdk": "org.freedesktop.Sdk",
  "finish-args": [
    "--device=dri",
    "--share=ipc",
    "--share=network",
    "--socket=x11",
    "--socket=pulseaudio",
    "--persist=.dosbox"
  ],
  "command": "dosbox-wrapper",
  "cleanup": [
    "/include",
    "/lib/pkgconfig",
    "/share/aclocal",
    "/share/man",
    "*.la", "*.a"
  ],
  "modules": [
    "../shared-modules/glu/glu-9.json",
    "../shared-modules/SDL/SDL-1.2.15.json",
    "../shared-modules/SDL/SDL_net-1.2.8.json",
    "../shared-modules/smpeg/smpeg-0.4.5.json",
    {
      "name": "SDL_sound",
      "build-options": {
        "cflags": "-I /app/include/smpeg/",
        "cppflags": "-I /app/include/smpeg/",
        "cxxflags": "-I /app/include/smpeg/"
      },
      "sources": [
        {
          "type": "archive",
          "url": "https://icculus.org/SDL_sound/downloads/SDL_sound-1.0.3.tar.gz",
          "sha256": "3999fd0bbb485289a52be14b2f68b571cb84e380cc43387eadf778f64c79e6df"
        }
      ]
    },
    {
      "name": "dosbox",
      "sources": [
        {
          "type": "svn",
          "url": "https://svn.code.sf.net/p/dosbox/code-0/dosbox/trunk"
        },
        {
          "type": "file",
          "path": "com.dosbox.DOSBox.png"
        },
        {
          "type": "file",
          "path": "com.dosbox.DOSBox.appdata.xml"
        },
        {
          "type": "file",
          "path": "com.dosbox.DOSBox.desktop"
        },
        {
          "type": "file",
          "path": "dosbox-wrapper.sh"
        }
      ],
      "post-install": [
        "install -Dm644 com.dosbox.DOSBox.appdata.xml /app/share/appdata/com.dosbox.DOSBox.appdata.xml",
        "install -Dm644 com.dosbox.DOSBox.desktop /app/share/applications/com.dosbox.DOSBox.desktop",
        "install -Dm644 com.dosbox.DOSBox.png /app/share/icons/hicolor/256x256/apps/com.dosbox.DOSBox.png",
        "install -Dm755 dosbox-wrapper.sh /app/bin/dosbox-wrapper"
      ]
    }
  ]
}
